Consolidate_csv_files_from_gcs/__init__.py
Consolidate_csv_files_from_gcs/main.py
Consolidate_csv_files_from_gcs-0.1.dist-info/METADATA
Consolidate_csv_files_from_gcs-0.1.dist-info/WHEEL
Consolidate_csv_files_from_gcs-0.1.dist-info/entry_points.txt
Consolidate_csv_files_from_gcs-0.1.dist-info/top_level.txt
Consolidate_csv_files_from_gcs-0.1.dist-info/RECORD
