Metadata-Version: 2.1
Name: Consolidate_csv_files_from_gcs
Version: 0.1
